Phase 2/hockey.v
module hockey(

    input clk,
    input rst,
    
    input BTN_A,
    input BTN_B,
    
    input [1:0] DIR_A,
    input [1:0] DIR_B,
    
    input [2:0] Y_in_A,
    input [2:0] Y_in_B,
   
    /*output reg LEDA,
    output reg LEDB,
    output reg [4:0] LEDX,
    
    output reg [6:0] SSD7,
    output reg [6:0] SSD6,
    output reg [6:0] SSD5,
    output reg [6:0] SSD4, 
    output reg [6:0] SSD3,
    output reg [6:0] SSD2,
    output reg [6:0] SSD1,
    output reg [6:0] SSD0   */

    output reg [2:0] X_COORD,
	output reg [2:0] Y_COORD

    );    

    reg [1:0] Y_DIR;
    
    reg [3:0] current_state; 

    parameter IDLE = 0, DISP = 1;
    parameter HIT_A = 2, HIT_B = 3; 
    parameter SEND_A = 4, SEND_B = 5;
    parameter RESP_A = 6, RESP_B = 7;
    parameter GOAL_A = 8, GOAL_B = 9;
    parameter END_GAME = 10;

    reg [1:0] score_A;
    reg [1:0] score_B;

    reg turn;

    reg [7:0] timer;
    reg timer_amount;
    
    always @(posedge clk or posedge rst)
    begin

        if(rst) begin
            X_COORD <= 3'b000;
            Y_COORD <= 3'b000;
            Y_DIR <= 3'b000;
            timer <= 7'b0000000;
            timer_amount <= 200;
            turn <= 1'b0;
            score_A <= 2'b00;
            score_B <= 2'b00;

            current_state <= IDLE;
        end

        else
            begin
                case(current_state)

                IDLE: begin
                    if((BTN_A == 1'b1) && (BTN_B == 1'b0)) begin
                        turn <= 1'b0;
                        current_state <= DISP;
                    end 
                    else if((BTN_A == 1'b0) && (BTN_B == 1'b1)) begin
                        turn <= 1'b1;
                        current_state <= DISP;
                    end 
                    else begin
                        current_state <= IDLE;
                    end                    
                end

                DISP: begin

                    if (turn == 0) begin // Hit A

                        if (timer == timer_amount) begin

                            current_state <= HIT_A;
                            timer <= 0;
                        end

                        else begin
                            timer <= timer + 1;
                            current_state <= DISP;
                        end                        
                    end

                    else if (turn == 1) begin
                        
                        if (timer == timer_amount) begin
                            current_state <= HIT_B;
                            timer <= 0;
                        end

                        else begin
                            timer <= timer + 1;
                            current_state <= DISP;
                        end                        
                    end

                    end

                HIT_A: begin

                    if(BTN_A && (Y_in_A < 5)) begin

                        X_COORD <= 3'b000;
                        Y_COORD <= Y_in_A;
                        Y_DIR <= DIR_A;

                        current_state <= SEND_B;
                    end

                    else begin
                        current_state <= HIT_A;
                    end
                end

                HIT_B: begin

                    if(BTN_B && (Y_in_B < 5)) begin

                        X_COORD <= 3'b100;
                        Y_COORD <= Y_in_B;
                        Y_DIR <= DIR_B;

                        current_state <= SEND_A;
                    end

                    else begin
                        current_state <= HIT_B;
                    end
                end

                SEND_A: begin
                    if (timer < timer_amount) 
                        begin
                            timer <= timer + 1;
                            current_state <= SEND_A;
                        end
                    else if (timer == timer_amount)
                        begin
                            timer <= 1'b0;
                            if (Y_DIR == 2'b10)
                                begin
                                    if (Y_COORD == 1'b0)
                                        begin
                                            Y_DIR<= 2'b01;
                                            Y_COORD <= Y_COORD + 1;
                                        end
                                    else
                                        begin
                                            Y_COORD <= Y_COORD - 1;
                                        end
                                end
                            else if (Y_DIR == 2'b01)
                                begin
                                    if (Y_COORD == 3'b100)
                                        begin
                                            Y_DIR <= 2'b10;
                                            Y_COORD <= Y_COORD - 1;
                                        end
                                    else 
                                        begin
                                            Y_COORD <= Y_COORD + 1;
                                        end
                                end
                            else if (Y_DIR == 2'b00)
                                begin

                                end
                        end

                        if (X_COORD > 1)
                            begin
                                X_COORD <= X_COORD - 1;
                                current_state <= SEND_A;
                            end
                        else
                            begin
                                X_COORD <= 3'b000;
                                current_state <= RESP_A;
                            end
                    end

                SEND_B: begin
                    if (timer < timer_amount) 
                        begin
                            timer <= timer + 1;
                            current_state <= SEND_B;
                        end
                    else if (timer == timer_amount)
                        begin
                            timer <= 0;
                            if (Y_DIR == 2'b10)
                                begin
                                    if (Y_COORD == 3'b000)
                                        begin
                                            Y_DIR<= 2'b01;
                                            Y_COORD <= Y_COORD + 1;
                
                                        end
                                    else
                                        begin
                                            Y_COORD <= Y_COORD - 1;
                                        end
                                end
                            else if (Y_DIR == 2'b01)
                                begin
                                    if (Y_COORD == 3'b100)
                                        begin
                                            Y_DIR <= 2'b10;
                                            Y_COORD <= Y_COORD - 1;
                                        end
                                    else 
                                        begin
                                            Y_COORD <= Y_COORD + 1;
                                        end
                                end
                            else if (Y_DIR == 2'b00)
                                begin
                
                                end
                        end
                
                    if (X_COORD < 3)
                        begin
                            X_COORD <= X_COORD + 1;
                            current_state <= SEND_B;
                        end
                    else
                        begin
                            X_COORD <= 3'b100;
                            current_state <= RESP_B;
                        end
                end

                RESP_A:
                    begin
                        if (timer < timer_amount)
                            begin
                                if (BTN_A && (Y_COORD == Y_in_A))
                                    begin
                                        X_COORD <= 3'b001;
                                        timer <= 0;
                                        if (DIR_B == 2'b00)
                                            begin
                                                Y_DIR <= DIR_B;
                                                current_state <= SEND_B;
                                            end
                                        else if (DIR_B == 2'b01)
                                            begin
                                                if (Y_COORD == 3'b100)
                                                    begin
                                                        Y_DIR <= 2'b10;
                                                        Y_COORD <= Y_COORD - 1;
                                                        current_state <= SEND_B;
                                                    end
                                                else
                                                    begin
                                                        Y_DIR <= DIR_A;
                                                        Y_COORD <= Y_COORD + 1;
                                                        current_state <= SEND_B;
                                                    end
                                            end
                                        else if (DIR_B == 2'b10)
                                            begin
                                                if (Y_COORD == 3'b000)
                                                    begin
                                                        Y_DIR <= 2'b01;
                                                        Y_COORD <= Y_COORD + 1;
                                                        current_state <= SEND_B;
                                                    end
                                                else
                                                    begin
                                                        Y_DIR <= DIR_A;
                                                        Y_COORD <= Y_COORD - 1;
                                                        current_state <= SEND_B;
                                                    end
                                            end
                                    end
                                else 
                                    begin
                                        timer <= timer + 1;
                                        current_state <= RESP_A;
                                    end
                            end
                        else if (timer == timer_amount)
                            begin
                                timer <= 0;
                                score_B <= score_B + 1;
                                current_state <= GOAL_B;
                            end
                    end

                GOAL_B:
                    begin
                        if (timer < timer_amount)
                            begin
                                timer <= timer + 1;
                                current_state <= GOAL_B;
                            end
                        else if (timer == timer_amount)
                            begin
                                timer <= 0;
                                if (score_B == 2'b11)
                                    begin
                                        turn <= 1'b1;
                                        current_state <= END_GAME;
                                    end
                                else if (score_B != 2'b11)
                                    begin
                                        current_state <= HIT_A;
                                    end
                            end
                    end

                GOAL_A:
                    begin
                        if (timer < timer_amount)
                            begin
                                timer <= timer + 1;
                                current_state <= GOAL_A;
                            end
                        else if (timer == timer_amount)
                            begin
                                timer <= 0;
                                if (score_A == 2'b11)
                                    begin
                                        turn <= 1'b0;
                                        current_state <= END_GAME;
                                    end
                                else if (score_A != 2'b11)
                                    begin
                                        current_state <= HIT_B;
                                    end
                            end
                    end

                RESP_B:
                    begin
                        if (timer < timer_amount)
                            begin
                                if (BTN_B && (Y_COORD == Y_in_B))
                                    begin
                                        X_COORD <= 3'b011;
                                        timer <= 0;
                                        if (DIR_A == 2'b00)
                                            begin
                                                Y_DIR <= DIR_A;
                                                current_state <= SEND_A;
                                            end
                                        else if (DIR_A == 2'b01)
                                            begin
                                                if (Y_COORD == 3'b100)
                                                    begin
                                                        Y_DIR <= 2'b10;
                                                        Y_COORD <= Y_COORD - 1;
                                                        current_state <= SEND_A;
                                                    end
                                                else if (Y_COORD != 3'b100)
                                                    begin
                                                        Y_DIR <= DIR_B;
                                                        Y_COORD <= Y_COORD + 1;
                                                        current_state <= SEND_A;
                                                    end
                                            end
                                        else if (DIR_A == 2'b10)
                                            begin
                                                if (Y_COORD == 3'b000)
                                                    begin
                                                        Y_DIR <= 2'b01;
                                                        Y_COORD <= Y_COORD + 1;
                                                        current_state <= SEND_A;
                                                    end
                                                else if (Y_COORD != 1'b0)
                                                    begin
                                                        Y_DIR <= DIR_B;
                                                        Y_COORD <= Y_COORD - 1;
                                                        current_state <= SEND_A;
                                                    end
                                            end
                                    end
                                else 
                                    begin
                                        timer <= timer + 1;
                                        current_state <= RESP_B;
                                    end
                            end
                        else if (timer == timer_amount)
                            begin
                                timer <= 0;
                                score_A <= score_A + 1;
                                current_state <= GOAL_A;
                            end
                    end

                END_GAME: 
                    begin
                        current_state <= END_GAME;
                    end


            endcase
        end
	end
endmodule

Phase 2/hockey_tb.v
module hockey_tb();


parameter HP = 5;       // Half period of our clock signal
parameter FP = (2*HP);  // Full period of our clock signal
parameter FFP = (3*FP);

reg clk, rst, BTN_A, BTN_B;
reg [1:0] DIR_A;
reg [1:0] DIR_B;
reg [2:0] Y_in_A;
reg [2:0] Y_in_B;

wire [2:0] X_COORD, Y_COORD;

// Our design-under-test is the DigiHockey module
hockey dut(clk, rst, BTN_A, BTN_B, DIR_A, DIR_B, Y_in_A, Y_in_B, X_COORD,Y_COORD);

// This always statement automatically cycles between clock high and clock low in HP (Half Period) time. Makes writing test-benches easier.
always #HP clk = ~clk;

initial begin
	$dumpfile("hockey.vcd"); 
	$dumpvars(0, hockey_tb); // Dump signals for tracing
    $display("Simulation started.");

    clk = 0; 
    rst = 0;
    BTN_A = 0;
	BTN_B = 0;
	DIR_A = 0;
	DIR_B = 0;
    Y_in_A = 0;
    Y_in_B = 0;
    
	#FP;
	rst=1;
	#FP;
	rst=0;

	// First Hit A - Starts
	
	BTN_A = 1;
	#FP;
	BTN_A = 0;

	#FP;
	Y_in_A = 1;
	DIR_A = 1;
	BTN_A = 1;
	#FP;
	BTN_A = 0;
	#FFP;

	// B couldnt Hit A:1 - B:0
	
	Y_in_B = 2;
	DIR_B = 0;
	BTN_B = 1;
	#FP;
	BTN_B = 0;
	#FFP;

	// Second Hit - B Starts
	
	Y_in_B = 2;
	DIR_B = 0;
	BTN_B = 1;
	#FP;
	BTN_B = 0;
	
	#FFP;
	Y_in_A = 1;
	DIR_A = 2;
	BTN_A = 1;
	#FP;
	BTN_A = 0;
	#FFP;
	
	// A couldnt Hit A:1 - B:1
	// Third hit - A starts 
	
	Y_in_A = 4;
	DIR_A = 2;
	BTN_A = 1;
	#FP;
	BTN_A = 0;
	#FFP;
	
	
	Y_in_B = 3;
	DIR_B = 0;
	BTN_B = 1;
	#FP;
	BTN_B = 0;
	#FFP;
	
	// B couldnt Hit A:2 - B:1
	// Fourth Hit - B Starts
	
	Y_in_B = 1;
	DIR_B = 2;
	BTN_B = 1;
	#FP;
	BTN_B = 0;
	#FFP;
	
	
	Y_in_A = 3;
	DIR_A = 0;
	BTN_A = 1;
	#FP;
	BTN_A = 0;
	#FFP;
	
	
	Y_in_B = 3;
	DIR_B = 1;
	BTN_B = 1;
	#FP;
	BTN_B = 0;
	#FFP;
	
	
	Y_in_A = 1;
	DIR_A = 2;
	BTN_A = 1;
	#FP;
	BTN_A = 0;
	#FFP;
	
	
	Y_in_B = 2;
	DIR_B = 0;
	BTN_B = 1;
	#FP;
	BTN_B = 0;
	#FFP;
	#FFP;
	#FFP;
	#FFP;

	
	
	rst = 1;
	#FP
	rst= 0;
	$display("Simulation finished.");
	$finish();
end



endmodule

Phase 2/hockey.vcd
$date
	Tue Jan 02 11:45:19 2024
$end
$version
	Icarus Verilog
$end
$timescale
	1s
$end
$scope module hockey_tb $end
$var wire 3 ! Y_COORD [2:0] $end
$var wire 3 " X_COORD [2:0] $end
$var parameter 96 # FFP $end
$var parameter 64 $ FP $end
$var parameter 32 % HP $end
$var reg 1 & BTN_A $end
$var reg 1 ' BTN_B $end
$var reg 2 ( DIR_A [1:0] $end
$var reg 2 ) DIR_B [1:0] $end
$var reg 3 * Y_in_A [2:0] $end
$var reg 3 + Y_in_B [2:0] $end
$var reg 1 , clk $end
$var reg 1 - rst $end
$scope module dut $end
$var wire 1 & BTN_A $end
$var wire 1 ' BTN_B $end
$var wire 2 . DIR_A [1:0] $end
$var wire 2 / DIR_B [1:0] $end
$var wire 3 0 Y_in_A [2:0] $end
$var wire 3 1 Y_in_B [2:0] $end
$var wire 1 , clk $end
$var wire 1 - rst $end
$var parameter 32 2 DISP $end
$var parameter 32 3 END_GAME $end
$var parameter 32 4 GOAL_A $end
$var parameter 32 5 GOAL_B $end
$var parameter 32 6 HIT_A $end
$var parameter 32 7 HIT_B $end
$var parameter 32 8 IDLE $end
$var parameter 32 9 RESP_A $end
$var parameter 32 : RESP_B $end
$var parameter 32 ; SEND_A $end
$var parameter 32 < SEND_B $end
$var reg 3 = X_COORD [2:0] $end
$var reg 3 > Y_COORD [2:0] $end
$var reg 2 ? Y_DIR [1:0] $end
$var reg 4 @ current_state [3:0] $end
$var reg 2 A score_A [1:0] $end
$var reg 2 B score_B [1:0] $end
$var reg 8 C timer [7:0] $end
$var reg 1 D timer_amount $end
$var reg 1 E turn $end
$upscope $end
$upscope $end
$enddefinitions $end
$comment Show the parameter values. $end
$dumpall
b101 <
b100 ;
b111 :
b110 9
b0 8
b11 7
b10 6
b1001 5
b1000 4
b1010 3
b1 2
b101 %
b1010 $
b11110 #
$end
#0
$dumpvars
xE
xD
bx C
bx B
bx A
bx @
bx ?
bx >
bx =
b0 1
b0 0
b0 /
b0 .
0-
0,
b0 +
b0 *
b0 )
b0 (
0'
0&
bx "
bx !
$end
#5
1,
#10
b0 @
b0 B
b0 A
0E
0D
b0 C
b0 ?
b0 !
b0 >
b0 "
b0 =
0,
1-
#15
1,
#20
0,
1&
0-
#25
b1 @
1,
#30
0,
0&
#35
b10 @
1,
#40
0,
1&
b1 (
b1 .
b1 *
b1 0
#45
b101 @
b1 ?
b1 !
b1 >
1,
#50
0,
0&
#55
b1 "
b1 =
b10 !
b10 >
1,
#60
0,
#65
b10 "
b10 =
b11 !
b11 >
1,
#70
0,
#75
b11 "
b11 =
b100 !
b100 >
1,
#80
0,
1'
b10 +
b10 1
#85
b111 @
b100 "
b100 =
b11 !
b11 >
b10 ?
1,
#90
0,
0'
#95
b1000 @
b1 A
1,
#100
0,
#105
b11 @
1,
#110
0,
#115
1,
#120
0,
1'
#125
b100 @
b0 ?
b10 !
b10 >
1,
#130
0,
0'
#135
b11 "
b11 =
1,
#140
0,
#145
b10 "
b10 =
1,
#150
0,
#155
b1 "
b1 =
1,
#160
0,
1&
b10 (
b10 .
#165
b110 @
b0 "
b0 =
1,
#170
0,
0&
#175
b1001 @
b1 B
1,
#180
0,
#185
b10 @
1,
#190
0,
#195
1,
#200
0,
1&
b100 *
b100 0
#205
b101 @
b10 ?
b100 !
b100 >
1,
#210
0,
0&
#215
b1 "
b1 =
b11 !
b11 >
1,
#220
0,
#225
b10 "
b10 =
b10 !
b10 >
1,
#230
0,
#235
b11 "
b11 =
b1 !
b1 >
1,
#240
0,
1'
b11 +
b11 1
#245
b111 @
b100 "
b100 =
b0 !
b0 >
1,
#250
0,
0'
#255
b1000 @
b10 A
1,
#260
0,
#265
b11 @
1,
#270
0,
#275
1,
#280
0,
1'
b10 )
b10 /
b1 +
b1 1
#285
b100 @
b1 !
b1 >
1,
#290
0,
0'
#295
b11 "
b11 =
b0 !
b0 >
1,
#300
0,
#305
b10 "
b10 =
b1 !
b1 >
b1 ?
1,
#310
0,
#315
b1 "
b1 =
b10 !
b10 >
1,
#320
0,
1&
b0 (
b0 .
b11 *
b11 0
#325
b110 @
b0 "
b0 =
b11 !
b11 >
1,
#330
0,
0&
#335
b1001 @
b10 B
1,
#340
0,
#345
b10 @
1,
#350
0,
#355
1,
#360
0,
1'
b1 )
b1 /
b11 +
b11 1
#365
1,
#370
0,
0'
#375
1,
#380
0,
#385
1,
#390
0,
#395
1,
#400
0,
1&
b10 (
b10 .
b1 *
b1 0
#405
b101 @
b10 ?
b1 !
b1 >
1,
#410
0,
0&
#415
b1 "
b1 =
b0 !
b0 >
1,
#420
0,
#425
b10 "
b10 =
b1 !
b1 >
b1 ?
1,
#430
0,
#435
b11 "
b11 =
b10 !
b10 >
1,
#440
0,
1'
b0 )
b0 /
b10 +
b10 1
#445
b111 @
b100 "
b100 =
b11 !
b11 >
1,
#450
0,
0'
#455
b1000 @
b11 A
1,
#460
0,
#465
b1010 @
1,
#470
0,
#475
1,
#480
0,
#485
1,
#490
0,
#495
1,
#500
0,
#505
1,
#510
0,
#515
1,
#520
0,
#525
1,
#530
0,
#535
1,
#540
0,
#545
1,
#550
0,
#555
1,
#560
0,
#565
1,
#570
b0 @
b0 B
b0 A
b0 ?
b0 !
b0 >
b0 "
b0 =
0,
1-
#575
1,
#580
0,
0-
